LICENSE
MANIFEST.in
README.md
setup.py
bin/sinklog
python_sinklog.egg-info/PKG-INFO
python_sinklog.egg-info/SOURCES.txt
python_sinklog.egg-info/dependency_links.txt
python_sinklog.egg-info/top_level.txt
sinklog/__init__.py
sinklog/handler.py